api_generator/__init__.py
api_generator/main.py
api_generator/generator/__init__.py
api_generator/generator/base_generator.py
api_generator/generator/generator.py
api_generator/generator/express_js/__init__.py
api_generator/generator/express_js/expressjs_generator.py
api_generator/generator/express_js/templates/__init__.py
api_generator/generator/express_js/templates/templates.py
api_generator/generator/fast_api/__init__.py
api_generator/generator/fast_api/fast_api_generator.py
api_generator/generator/fast_api/templates/__init__.py
api_generator/generator/fast_api/templates/templates.py
api_generator/generator/python/__init__.py
api_generator/generator/python/python_generator.py
api_generator/generator/python/templates/__init__.py
api_generator/generator/python/templates/templates.py
api_generator/generator/python_bottle/__init__.py
api_generator/generator/python_bottle/python_bottle_generator.py
api_generator/generator/python_bottle/templates/__init__.py
api_generator/generator/python_bottle/templates/templates.py
api_generator/generator/python_flask/__init__.py
api_generator/generator/python_flask/python_flask_generator.py
api_generator/generator/python_flask/templates/__init__.py
api_generator/generator/python_flask/templates/templates.py
api_generator/store/__init__.py
api_generator/store/store.py
api_generator/utils/__init__.py
api_generator/utils/filter_placeholders.py
api_generator/utils/generate_uuid.py
api_generator/utils/logger.py
api_generator/utils/render_template.py
api_generator/utils/text_to_buffer.py
loop_api_generator-0.9.4.dist-info/LICENSE
loop_api_generator-0.9.4.dist-info/METADATA
loop_api_generator-0.9.4.dist-info/WHEEL
loop_api_generator-0.9.4.dist-info/top_level.txt
loop_api_generator-0.9.4.dist-info/RECORD
